machinelearnnning/__init__.py
machinelearnnning/prac1.py
machinelearnnning/prac2.py
machinelearnnning/prac3.py
machinelearnnning/prac4.py
machinelearnnning/prac5.py
machinelearnnning/prac6.py
machinelearnnning/prac7.py
machinelearnnning-0.1.2.dist-info/licenses/LICENSE
machinelearnnning-0.1.2.dist-info/METADATA
machinelearnnning-0.1.2.dist-info/WHEEL
machinelearnnning-0.1.2.dist-info/top_level.txt
machinelearnnning-0.1.2.dist-info/RECORD
