Metadata-Version: 2.4
Name: machinelearnnning
Version: 0.1.2
Summary: A simple machine learning practice package with practicals (prac1–prac7).
Author: Enzo Martini
Author-email: Enzo Martini <enzomartini.1995@gmail.com>
License: MIT License
Project-URL: Homepage, https://github.com/enzomartini1995-del/machinelearnnning
Project-URL: Bug Tracker, https://github.com/enzomartini1995-del/machinelearnnning
Requires-Python: >=3.6
License-File: LICENSE
Dynamic: author
Dynamic: license-file
Dynamic: requires-python
